{
    "apps": [
        {
            "name": "ledn_server_local",
            "script": "./dist/src/app.js",
            "env_local": {
                "NODE_ENV": "development",
                "LEDN_PORT": 3000,
                "LEDN_MONGO_USER": "ledn_admin",
                "LEDN_MONGO_PASSWORD": "ledn_password",
                "LEDN_MONGO_HOSTNAME": "localhost",
                "LEDN_MONGO_DB": "ledndb",
                "LEDN_MONGO_PORT": 27017,
                "LEDN_DEFAULT_PAGE_SIZE": 20
            }
        },
        {
            "name": "ledn_server_dev",
            "script": "./dist/src/app.js",
            "env_development": {
                "NODE_ENV": "development",
                "LEDN_PORT": 3000,
                "LEDN_MONGO_USER": "ledn_admin",
                "LEDN_MONGO_PASSWORD": "ledn_password",
                "LEDN_MONGO_HOSTNAME": "mongodb",
                "LEDN_MONGO_DB": "ledndb",
                "LEDN_MONGO_PORT": 27017,
                "LEDN_DEFAULT_PAGE_SIZE": 20
            }
        },
        {
            "name": "ledn_server_prod",
            "script": "./dist/src/app.js",
            "env_production": {
                "NODE_ENV": "production",
                "LEDN_PORT": 3000,
                "LEDN_MONGO_USER": "ledn_admin",
                "LEDN_MONGO_PASSWORD": "ledn_password",
                "LEDN_MONGO_HOSTNAME": "mongodb",
                "LEDN_MONGO_DB": "ledndb",
                "LEDN_MONGO_PORT": 27017,
                "LEDN_DEFAULT_PAGE_SIZE": 20
            }
        }
    ]
}